opta/__init__.py
opta/algorithms/__init__.py
opta/algorithms/abstract_algorithm.py
opta/algorithms/black_hole_optimization.py
opta/algorithms/explosion_search.py
opta/algorithms/flower_pollination_algorithm.py
opta/algorithms/particle_swarm_optimization.py
opta/algorithms/random_search.py
opta/tools/__init__.py
opta/tools/custom_encoding.py
opta/tools/testing.py
opta/tools/vectors.py
opta-0.7.0.dist-info/LICENSE
opta-0.7.0.dist-info/METADATA
opta-0.7.0.dist-info/WHEEL
opta-0.7.0.dist-info/RECORD
