Metadata-Version: 2.3
Name: opta
Version: 0.7.0
Summary: 
License: MIT
Author: wol4aravio
Author-email: panovskiy.v@yandex.ru
Requires-Python: >=3.10,<4.0
Classifier: License :: OSI Approved :: MIT License
Classifier: Programming Language :: Python :: 3
Classifier: Programming Language :: Python :: 3.10
Classifier: Programming Language :: Python :: 3.11
Classifier: Programming Language :: Python :: 3.12
Classifier: Programming Language :: Python :: 3.13
Requires-Dist: numpy (>=2.2.4,<3.0.0)
